cm2util/__init__.py
cm2util/cm2circ.py
cm2util/cm2compress.py
cm2util/cm2img.py
cm2util/cm2mem.py
cm2util-0.1.dist-info/METADATA
cm2util-0.1.dist-info/WHEEL
cm2util-0.1.dist-info/licenses/LICENSE
cm2util-0.1.dist-info/RECORD
