Metadata-Version: 2.1
Name: cm2util
Version: 0.1
Summary: A collection of utility modules to aid in the creation of Circuit Maker 2 builds.
Project-URL: Homepage, https://github.com/triducal/cm2util
Project-URL: Issues, https://github.com/triducal/cm2util/issues
Author-email: Triducal <triducalrl@gmail.com>
License-File: LICENSE
Classifier: License :: OSI Approved :: MIT License
Classifier: Operating System :: OS Independent
Classifier: Programming Language :: Python :: 3
Requires-Python: >=3.8
Requires-Dist: cm2py
Requires-Dist: numpy
Requires-Dist: pillow
Requires-Dist: requests
